{"favorited": false, "contributors": null, "truncated": false, "text": "Google a pas innov\u00e9 avec un tamagochi, ils ont tout compris #google #nexusprime", "is_quote_status": false, "in_reply_to_status_id": null, "user": {"follow_request_sent": false, "has_extended_profile": true, "profile_use_background_image": true, "default_profile_image": false, "id": 18549853, "profile_background_image_url_https": "https://pbs.twimg.com/profile_background_images/138666164/flow1.jpg", "verified": false, "translator_type": "none", "profile_text_color": "22546B", "profile_image_url_https": "https://pbs.twimg.com/profile_images/738214830222548992/Z75dV7lK_normal.jpg", "profile_sidebar_fill_color": "64CDD3", "entities": {"url": {"urls": [{"url": "https://t.co/asJIKIGxza", "indices": [0, 23], "expanded_url": "https://www.edouard-marquez.me", "display_url": "edouard-marquez.me"}]}, "description": {"urls": []}}, "followers_count": 4206, "profile_sidebar_border_color": "C5EFED", "id_str": "18549853", "profile_background_color": "5FC7D9", "listed_count": 286, "is_translation_enabled": false, "utc_offset": 3600, "statuses_count": 40374, "description": "D\u00e9veloppeur Android freelance et membre du @ParisAndroidUG", "friends_count": 889, "location": "Paris, France", "profile_link_color": "DD2E44", "profile_image_url": "http://pbs.twimg.com/profile_images/738214830222548992/Z75dV7lK_normal.jpg", "following": false, "geo_enabled": true, "profile_banner_url": "https://pbs.twimg.com/profile_banners/18549853/1464839207", "profile_background_image_url": "http://pbs.twimg.com/profile_background_images/138666164/flow1.jpg", "screen_name": "g123k", "lang": "en", "profile_background_tile": true, "favourites_count": 90, "name": "Edouard Marquez", "notifications": false, "url": "https://t.co/asJIKIGxza", "created_at": "Fri Jan 02 10:28:32 +0000 2009", "contributors_enabled": false, "time_zone": "Paris", "protected": false, "default_profile": false, "is_translator": false}, "geo": null, "id": 126491723353427968, "favorite_count": 0, "lang": "fr", "source": "<a href=\"https://about.twitter.com/products/tweetdeck\" rel=\"nofollow\">TweetDeck</a>", "created_at": "Wed Oct 19 02:55:51 +0000 2011", "retweeted": false, "coordinates": null, "in_reply_to_user_id_str": null, "entities": {"symbols": [], "user_mentions": [], "hashtags": [{"indices": [60, 67], "text": "google"}, {"indices": [68, 79], "text": "nexusprime"}], "urls": []}, "in_reply_to_status_id_str": null, "in_reply_to_screen_name": null, "in_reply_to_user_id": null, "place": null, "retweet_count": 1, "id_str": "126491723353427968"}
