{"favorited": false, "contributors": null, "truncated": false, "text": "#Google #Cloud Service Blackouts Threaten Cloud Users: During a 30-day period in August and September, for ... http://t.co/G0ElVRVJ #TCN", "is_quote_status": false, "in_reply_to_status_id": null, "user": {"follow_request_sent": false, "has_extended_profile": false, "profile_use_background_image": true, "default_profile_image": false, "id": 24609329, "profile_background_image_url_https": "https://abs.twimg.com/images/themes/theme1/bg.png", "verified": false, "translator_type": "none", "profile_text_color": "333333", "profile_image_url_https": "https://pbs.twimg.com/profile_images/541608022712147968/LuZzuQY-_normal.png", "profile_sidebar_fill_color": "DDEEF6", "entities": {"description": {"urls": [{"url": "https://t.co/OtTzQlGhLc", "indices": [62, 85], "expanded_url": "http://flip.it/itxpc", "display_url": "flip.it/itxpc"}]}}, "followers_count": 42997, "profile_sidebar_border_color": "C0DEED", "id_str": "24609329", "profile_background_color": "C0DEED", "listed_count": 1616, "is_translation_enabled": false, "utc_offset": -21600, "statuses_count": 469991, "description": "#Opines on #Cloud by @OpineMediaGroup (OMG). Now on Flipboard https://t.co/OtTzQlGhLc - Submit content to cloud@pr2web.com. Buy Followers are Blocked.", "friends_count": 41354, "location": "", "profile_link_color": "1DA1F2", "profile_image_url": "http://pbs.twimg.com/profile_images/541608022712147968/LuZzuQY-_normal.png", "following": false, "geo_enabled": true, "profile_banner_url": "https://pbs.twimg.com/profile_banners/24609329/1406905577", "profile_background_image_url": "http://abs.twimg.com/images/themes/theme1/bg.png", "screen_name": "TheCloudNetwork", "lang": "en", "profile_background_tile": false, "favourites_count": 1148, "name": "The Cloud Network\u2601\ufe0f", "notifications": false, "url": null, "created_at": "Sun Mar 15 23:38:56 +0000 2009", "contributors_enabled": false, "time_zone": "Saskatchewan", "protected": false, "default_profile": true, "is_translator": false}, "geo": null, "id": 126516572343910400, "possibly_sensitive": false, "possibly_sensitive_appealable": false, "lang": "en", "source": "<a href=\"http://twitterfeed.com\" rel=\"nofollow\">twitterfeed</a>", "created_at": "Wed Oct 19 04:34:36 +0000 2011", "retweeted": false, "coordinates": null, "in_reply_to_user_id_str": null, "entities": {"symbols": [], "user_mentions": [], "hashtags": [{"indices": [0, 7], "text": "Google"}, {"indices": [8, 14], "text": "Cloud"}, {"indices": [132, 136], "text": "TCN"}], "urls": [{"url": "http://t.co/G0ElVRVJ", "indices": [111, 131], "expanded_url": "http://bit.ly/pSL26S", "display_url": "bit.ly/pSL26S"}]}, "in_reply_to_status_id_str": null, "id_str": "126516572343910400", "in_reply_to_screen_name": null, "favorite_count": 0, "place": null, "retweet_count": 0, "in_reply_to_user_id": null}
