{"favorited": false, "contributors": null, "truncated": false, "text": "RT @businessuplift: Why #facebook and #google have got it wrong http://t.co/PDbF7H3f", "is_quote_status": false, "in_reply_to_status_id": null, "user": {"follow_request_sent": false, "has_extended_profile": false, "profile_use_background_image": true, "default_profile_image": false, "id": 80778850, "profile_background_image_url_https": "https://pbs.twimg.com/profile_background_images/70909241/Roger_IPhone_1387.JPG", "verified": false, "translator_type": "none", "profile_text_color": "3E4415", "profile_image_url_https": "https://pbs.twimg.com/profile_images/2275397356/image_normal.jpg", "profile_sidebar_fill_color": "99CC33", "entities": {"description": {"urls": []}}, "followers_count": 216, "profile_sidebar_border_color": "829D5E", "id_str": "80778850", "profile_background_color": "352726", "listed_count": 9, "is_translation_enabled": false, "utc_offset": -21600, "statuses_count": 6576, "description": "This is me and nobody else!\n\n\nCoffee Roaster", "friends_count": 418, "location": "us", "profile_link_color": "D02B55", "profile_image_url": "http://pbs.twimg.com/profile_images/2275397356/image_normal.jpg", "following": false, "geo_enabled": true, "profile_banner_url": "https://pbs.twimg.com/profile_banners/80778850/1423458693", "profile_background_image_url": "http://pbs.twimg.com/profile_background_images/70909241/Roger_IPhone_1387.JPG", "screen_name": "Magmacoffee", "lang": "en", "profile_background_tile": true, "favourites_count": 157, "name": "Roger Wright", "notifications": false, "url": null, "created_at": "Thu Oct 08 05:59:47 +0000 2009", "contributors_enabled": false, "time_zone": "Central Time (US & Canada)", "protected": false, "default_profile": false, "is_translator": false}, "geo": null, "id": 126526648928579584, "possibly_sensitive": false, "possibly_sensitive_appealable": false, "lang": "en", "retweeted_status": {"contributors": null, "truncated": false, "text": "Why #facebook and #google have got it wrong http://t.co/PDbF7H3f", "is_quote_status": false, "in_reply_to_status_id": null, "id": 126293028674609152, "favorite_count": 0, "source": "<a href=\"http://www.hootsuite.com\" rel=\"nofollow\">Hootsuite</a>", "retweeted": false, "coordinates": null, "entities": {"symbols": [], "user_mentions": [], "hashtags": [{"indices": [4, 13], "text": "facebook"}, {"indices": [18, 25], "text": "google"}], "urls": [{"url": "http://t.co/PDbF7H3f", "indices": [44, 64], "expanded_url": "http://ow.ly/1yPD7a", "display_url": "ow.ly/1yPD7a"}]}, "in_reply_to_screen_name": null, "in_reply_to_user_id": null, "retweet_count": 1, "id_str": "126293028674609152", "favorited": false, "user": {"follow_request_sent": false, "has_extended_profile": false, "profile_use_background_image": true, "default_profile_image": false, "id": 171947848, "profile_background_image_url_https": "https://pbs.twimg.com/profile_background_images/561434252/TwitterBackground123.jpg", "verified": false, "translator_type": "none", "profile_text_color": "333333", "profile_image_url_https": "https://pbs.twimg.com/profile_images/1089843191/Steve_Image_normal.jpg", "profile_sidebar_fill_color": "DDEEF6", "entities": {"url": {"urls": [{"url": "http://t.co/5MZUV0wO9S", "indices": [0, 22], "expanded_url": "http://www.businessuplift.com", "display_url": "businessuplift.com"}]}, "description": {"urls": []}}, "followers_count": 1073, "profile_sidebar_border_color": "C0DEED", "id_str": "171947848", "profile_background_color": "FFFFFF", "listed_count": 37, "is_translation_enabled": false, "utc_offset": 0, "statuses_count": 11896, "description": "A place where business owners & workers of the world 2.0 will find #business, #political & #economic updates (& occasional joke) which inform,enrich & entertain", "friends_count": 976, "location": "UK, Australia & Global Citizen", "profile_link_color": "0943F0", "profile_image_url": "http://pbs.twimg.com/profile_images/1089843191/Steve_Image_normal.jpg", "following": false, "geo_enabled": false, "profile_background_image_url": "http://pbs.twimg.com/profile_background_images/561434252/TwitterBackground123.jpg", "screen_name": "businessuplift", "lang": "en", "profile_background_tile": false, "favourites_count": 144, "name": "Steve Pollard", "notifications": false, "url": "http://t.co/5MZUV0wO9S", "created_at": "Wed Jul 28 15:16:07 +0000 2010", "contributors_enabled": false, "time_zone": "London", "protected": false, "default_profile": false, "is_translator": false}, "geo": null, "in_reply_to_user_id_str": null, "possibly_sensitive": false, "possibly_sensitive_appealable": false, "lang": "en", "created_at": "Tue Oct 18 13:46:19 +0000 2011", "in_reply_to_status_id_str": null, "place": null}, "source": "<a href=\"http://twitter.com/download/iphone\" rel=\"nofollow\">Twitter for iPhone</a>", "created_at": "Wed Oct 19 05:14:38 +0000 2011", "retweeted": false, "coordinates": null, "in_reply_to_user_id_str": null, "entities": {"symbols": [], "user_mentions": [{"id": 171947848, "indices": [3, 18], "id_str": "171947848", "screen_name": "businessuplift", "name": "Steve Pollard"}], "hashtags": [{"indices": [24, 33], "text": "facebook"}, {"indices": [38, 45], "text": "google"}], "urls": [{"url": "http://t.co/PDbF7H3f", "indices": [64, 84], "expanded_url": "http://ow.ly/1yPD7a", "display_url": "ow.ly/1yPD7a"}]}, "in_reply_to_status_id_str": null, "id_str": "126526648928579584", "in_reply_to_screen_name": null, "favorite_count": 0, "place": null, "retweet_count": 1, "in_reply_to_user_id": null}
