{"favorited": false, "contributors": null, "truncated": false, "text": "#OmniTouch - ekran dotykowy na d\u0142oni od #Microsoft. Czytaj wi\u0119cej @PGSTech http://t.co/Ec6mzWiz", "is_quote_status": false, "in_reply_to_status_id": null, "user": {"follow_request_sent": false, "has_extended_profile": false, "profile_use_background_image": true, "default_profile_image": false, "id": 330961772, "profile_background_image_url_https": "https://pbs.twimg.com/profile_background_images/294475845/Twitter_background2.jpg", "verified": false, "translator_type": "none", "profile_text_color": "333333", "profile_image_url_https": "https://pbs.twimg.com/profile_images/1453030229/Twitter_logo_v2_normal.jpg", "profile_sidebar_fill_color": "F3F3F3", "entities": {"url": {"urls": [{"url": "http://t.co/L0pfzen8Qo", "indices": [0, 22], "expanded_url": "http://tech.pgs-soft.com", "display_url": "tech.pgs-soft.com"}]}, "description": {"urls": []}}, "followers_count": 965, "profile_sidebar_border_color": "D9C1A7", "id_str": "330961772", "profile_background_color": "C0C0C4", "listed_count": 3, "is_translation_enabled": false, "utc_offset": 3600, "statuses_count": 1154, "description": "", "friends_count": 31, "location": "", "profile_link_color": "D43100", "profile_image_url": "http://pbs.twimg.com/profile_images/1453030229/Twitter_logo_v2_normal.jpg", "following": false, "geo_enabled": false, "profile_background_image_url": "http://pbs.twimg.com/profile_background_images/294475845/Twitter_background2.jpg", "screen_name": "PGStech", "lang": "en", "profile_background_tile": false, "favourites_count": 0, "name": "PGStech", "notifications": false, "url": "http://t.co/L0pfzen8Qo", "created_at": "Thu Jul 07 12:43:51 +0000 2011", "contributors_enabled": false, "time_zone": "Warsaw", "protected": false, "default_profile": false, "is_translator": false}, "geo": null, "id": 126625265928515584, "possibly_sensitive": false, "possibly_sensitive_appealable": false, "lang": "pl", "source": "<a href=\"http://twitter.com\" rel=\"nofollow\">Twitter Web Client</a>", "created_at": "Wed Oct 19 11:46:30 +0000 2011", "retweeted": false, "coordinates": null, "in_reply_to_user_id_str": null, "entities": {"symbols": [], "user_mentions": [{"id": 330961772, "indices": [66, 74], "id_str": "330961772", "screen_name": "PGStech", "name": "PGStech"}], "hashtags": [{"indices": [0, 10], "text": "OmniTouch"}, {"indices": [40, 50], "text": "Microsoft"}], "urls": [{"url": "http://t.co/Ec6mzWiz", "indices": [75, 95], "expanded_url": "http://bit.ly/ofmb9I", "display_url": "bit.ly/ofmb9I"}]}, "in_reply_to_status_id_str": null, "id_str": "126625265928515584", "in_reply_to_screen_name": null, "favorite_count": 0, "place": null, "retweet_count": 0, "in_reply_to_user_id": null}
