{"favorited": false, "contributors": null, "truncated": false, "text": "RT @VentureBeat: #Ballmer: \u201cWe\u2019ve picked our play\u201d in #social with #Skype deal http://t.co/03IHBOgj #microsoft #xbox #in", "is_quote_status": false, "in_reply_to_status_id": null, "user": {"follow_request_sent": false, "has_extended_profile": false, "profile_use_background_image": true, "default_profile_image": false, "id": 255433853, "profile_background_image_url_https": "https://abs.twimg.com/images/themes/theme1/bg.png", "verified": false, "translator_type": "none", "profile_text_color": "333333", "profile_image_url_https": "https://pbs.twimg.com/profile_images/1290542952/Foto_carnet_normal.jpg", "profile_sidebar_fill_color": "DDEEF6", "entities": {"description": {"urls": []}}, "followers_count": 400, "profile_sidebar_border_color": "C0DEED", "id_str": "255433853", "profile_background_color": "C0DEED", "listed_count": 27, "is_translation_enabled": false, "utc_offset": -10800, "statuses_count": 2472, "description": "", "friends_count": 342, "location": "Buenos Aires, Argentina", "profile_link_color": "1DA1F2", "profile_image_url": "http://pbs.twimg.com/profile_images/1290542952/Foto_carnet_normal.jpg", "following": false, "geo_enabled": false, "profile_background_image_url": "http://abs.twimg.com/images/themes/theme1/bg.png", "screen_name": "franbouzas", "lang": "es", "profile_background_tile": false, "favourites_count": 11, "name": "Francisco Bouzas", "notifications": false, "url": null, "created_at": "Mon Feb 21 10:38:23 +0000 2011", "contributors_enabled": false, "time_zone": "Buenos Aires", "protected": false, "default_profile": true, "is_translator": false}, "geo": null, "id": 126628527155052544, "possibly_sensitive": false, "possibly_sensitive_appealable": false, "lang": "en", "source": "<a href=\"http://www.flipboard.com\" rel=\"nofollow\">Flipboard</a>", "created_at": "Wed Oct 19 11:59:28 +0000 2011", "retweeted": false, "coordinates": null, "in_reply_to_user_id_str": null, "entities": {"symbols": [], "user_mentions": [{"id": 60642052, "indices": [3, 15], "id_str": "60642052", "screen_name": "VentureBeat", "name": "VentureBeat"}], "hashtags": [{"indices": [17, 25], "text": "Ballmer"}, {"indices": [54, 61], "text": "social"}, {"indices": [67, 73], "text": "Skype"}, {"indices": [100, 110], "text": "microsoft"}, {"indices": [111, 116], "text": "xbox"}, {"indices": [117, 120], "text": "in"}], "urls": [{"url": "http://t.co/03IHBOgj", "indices": [79, 99], "expanded_url": "http://bit.ly/nMPaXH", "display_url": "bit.ly/nMPaXH"}]}, "in_reply_to_status_id_str": null, "id_str": "126628527155052544", "in_reply_to_screen_name": null, "favorite_count": 0, "place": null, "retweet_count": 0, "in_reply_to_user_id": null}
