{"favorited": false, "contributors": null, "truncated": false, "text": "\u25ba #Job #IT #Projekt #Management #Microsoft  | Projekt f\u00fcr Freelancer: Programm Manager (m/w) in Berlin \u00bb http://t.co/MO4jtpTL", "is_quote_status": false, "in_reply_to_status_id": null, "user": {"follow_request_sent": false, "has_extended_profile": false, "profile_use_background_image": true, "default_profile_image": false, "id": 282515415, "profile_background_image_url_https": "https://pbs.twimg.com/profile_background_images/234478205/110413-SeitenHG-7-1900x950.png", "verified": false, "translator_type": "none", "profile_text_color": "333333", "profile_image_url_https": "https://pbs.twimg.com/profile_images/1312326511/avatar_300x300_normal.png", "profile_sidebar_fill_color": "EFEFEF", "entities": {"url": {"urls": [{"url": "http://t.co/3Lg00jWHrj", "indices": [0, 22], "expanded_url": "http://www.geco-group.com", "display_url": "geco-group.com"}]}, "description": {"urls": []}}, "followers_count": 79, "profile_sidebar_border_color": "EAEAEA", "id_str": "282515415", "profile_background_color": "8DA3B1", "listed_count": 77, "is_translation_enabled": false, "utc_offset": -10800, "statuses_count": 990, "description": "Dienstleistungsunternehmen. Wir rekrutieren und vermitteln freiberufliche IT-Experten.", "friends_count": 139, "location": "Schellerdamm 16, 21079 Hamburg", "profile_link_color": "DD2E44", "profile_image_url": "http://pbs.twimg.com/profile_images/1312326511/avatar_300x300_normal.png", "following": false, "geo_enabled": false, "profile_banner_url": "https://pbs.twimg.com/profile_banners/282515415/1483527166", "profile_background_image_url": "http://pbs.twimg.com/profile_background_images/234478205/110413-SeitenHG-7-1900x950.png", "screen_name": "GECO_Jobs", "lang": "de", "profile_background_tile": false, "favourites_count": 36, "name": "GECO Deutschland", "notifications": false, "url": "http://t.co/3Lg00jWHrj", "created_at": "Fri Apr 15 10:46:26 +0000 2011", "contributors_enabled": false, "time_zone": "Greenland", "protected": false, "default_profile": false, "is_translator": false}, "geo": null, "id": 126602212511203328, "possibly_sensitive": false, "possibly_sensitive_appealable": false, "lang": "de", "source": "<a href=\"http://twitter.com\" rel=\"nofollow\">Twitter Web Client</a>", "created_at": "Wed Oct 19 10:14:54 +0000 2011", "retweeted": false, "coordinates": null, "in_reply_to_user_id_str": null, "entities": {"symbols": [], "user_mentions": [], "hashtags": [{"indices": [2, 6], "text": "Job"}, {"indices": [7, 10], "text": "IT"}, {"indices": [11, 19], "text": "Projekt"}, {"indices": [20, 31], "text": "Management"}, {"indices": [32, 42], "text": "Microsoft"}], "urls": [{"url": "http://t.co/MO4jtpTL", "indices": [105, 125], "expanded_url": "http://tinyurl.com/GECO35142", "display_url": "tinyurl.com/GECO35142"}]}, "in_reply_to_status_id_str": null, "id_str": "126602212511203328", "in_reply_to_screen_name": null, "favorite_count": 0, "place": null, "retweet_count": 0, "in_reply_to_user_id": null}
