{"favorited": false, "contributors": null, "truncated": false, "text": "#sipcom supporting #arkadin at #ipexpo showing the advantages of #hosted #lync2010 for #enterprises #ucoms #MSFTnews #Microsoft #ucexpo #in", "is_quote_status": false, "in_reply_to_status_id": null, "user": {"follow_request_sent": false, "has_extended_profile": false, "profile_use_background_image": false, "default_profile_image": false, "id": 20142061, "profile_background_image_url_https": "https://abs.twimg.com/images/themes/theme15/bg.png", "verified": false, "translator_type": "none", "profile_text_color": "000000", "profile_image_url_https": "https://pbs.twimg.com/profile_images/569974809560629248/7PNGwaMI_normal.jpeg", "profile_sidebar_fill_color": "42D624", "entities": {"url": {"urls": [{"url": "http://t.co/LBxgkmPL7N", "indices": [0, 22], "expanded_url": "http://uk.linkedin.com/in/danielsipcom", "display_url": "uk.linkedin.com/in/danielsipcom"}]}, "description": {"urls": []}}, "followers_count": 801, "profile_sidebar_border_color": "FFFFFF", "id_str": "20142061", "profile_background_color": "000000", "listed_count": 34, "is_translation_enabled": false, "utc_offset": 0, "statuses_count": 645, "description": "Daniel is  SIPCOM's Founder & CEO, a  recognized industry leader with some of the world\u2019s top communications and software organizations.", "friends_count": 776, "location": "\u00dcT: 51.626955,0.037166", "profile_link_color": "000000", "profile_image_url": "http://pbs.twimg.com/profile_images/569974809560629248/7PNGwaMI_normal.jpeg", "following": false, "geo_enabled": true, "profile_background_image_url": "http://abs.twimg.com/images/themes/theme15/bg.png", "screen_name": "DanielSIPCOM", "lang": "en", "profile_background_tile": false, "favourites_count": 15, "name": "Daniel Allen", "notifications": false, "url": "http://t.co/LBxgkmPL7N", "created_at": "Thu Feb 05 12:07:36 +0000 2009", "contributors_enabled": false, "time_zone": "London", "protected": false, "default_profile": false, "is_translator": false}, "geo": null, "id": 126779541720010752, "favorite_count": 0, "lang": "en", "source": "<a href=\"http://blackberry.com/twitter\" rel=\"nofollow\">Twitter for BlackBerry\u00ae</a>", "created_at": "Wed Oct 19 21:59:32 +0000 2011", "retweeted": false, "coordinates": null, "in_reply_to_user_id_str": null, "entities": {"symbols": [], "user_mentions": [], "hashtags": [{"indices": [0, 7], "text": "sipcom"}, {"indices": [19, 27], "text": "arkadin"}, {"indices": [31, 38], "text": "ipexpo"}, {"indices": [65, 72], "text": "hosted"}, {"indices": [73, 82], "text": "lync2010"}, {"indices": [87, 99], "text": "enterprises"}, {"indices": [100, 106], "text": "ucoms"}, {"indices": [107, 116], "text": "MSFTnews"}, {"indices": [117, 127], "text": "Microsoft"}, {"indices": [128, 135], "text": "ucexpo"}, {"indices": [136, 139], "text": "in"}], "urls": []}, "in_reply_to_status_id_str": null, "in_reply_to_screen_name": null, "in_reply_to_user_id": null, "place": null, "retweet_count": 0, "id_str": "126779541720010752"}
