{"favorited": false, "contributors": null, "truncated": false, "text": "I'm not getting all of my @ replies #twitter if it wasn't for my emails telling me that some1 replied to me I wouldn't even know it #nobueno", "is_quote_status": false, "in_reply_to_status_id": null, "user": {"follow_request_sent": false, "has_extended_profile": true, "profile_use_background_image": true, "default_profile_image": false, "id": 68954343, "profile_background_image_url_https": "https://abs.twimg.com/images/themes/theme5/bg.gif", "verified": false, "translator_type": "none", "profile_text_color": "3E4415", "profile_image_url_https": "https://pbs.twimg.com/profile_images/608777974192721920/1XaIHQQk_normal.jpg", "profile_sidebar_fill_color": "99CC33", "entities": {"description": {"urls": []}}, "followers_count": 2548, "profile_sidebar_border_color": "829D5E", "id_str": "68954343", "profile_background_color": "352726", "listed_count": 98, "is_translation_enabled": false, "utc_offset": -18000, "statuses_count": 36816, "description": "Techie | loves dogs, fitness/running, NY sports, traveling, networking & new technologies| goal is to move to \u2600\ufe0f state in 2017", "friends_count": 79, "location": "Union County, NJ ", "profile_link_color": "D02B55", "profile_image_url": "http://pbs.twimg.com/profile_images/608777974192721920/1XaIHQQk_normal.jpg", "following": false, "geo_enabled": true, "profile_banner_url": "https://pbs.twimg.com/profile_banners/68954343/1466462654", "profile_background_image_url": "http://abs.twimg.com/images/themes/theme5/bg.gif", "screen_name": "mmelendez720", "lang": "en", "profile_background_tile": false, "favourites_count": 52, "name": "\u2133aria \u2133elendez", "notifications": false, "url": null, "created_at": "Wed Aug 26 11:22:32 +0000 2009", "contributors_enabled": false, "time_zone": "Eastern Time (US & Canada)", "protected": false, "default_profile": false, "is_translator": false}, "geo": {"type": "Point", "coordinates": [40.66989158, -74.27552285]}, "id": 126881658854064128, "favorite_count": 0, "lang": "en", "source": "<a href=\"http://twitter.com/download/iphone\" rel=\"nofollow\">Twitter for iPhone</a>", "created_at": "Thu Oct 20 04:45:19 +0000 2011", "retweeted": false, "coordinates": {"type": "Point", "coordinates": [-74.27552285, 40.66989158]}, "in_reply_to_user_id_str": null, "entities": {"symbols": [], "user_mentions": [], "hashtags": [{"indices": [36, 44], "text": "twitter"}, {"indices": [132, 140], "text": "nobueno"}], "urls": []}, "in_reply_to_status_id_str": null, "in_reply_to_screen_name": null, "in_reply_to_user_id": null, "place": {"country_code": "US", "url": "https://api.twitter.com/1.1/geo/id/bcab414422facfa5.json", "country": "United States", "place_type": "city", "bounding_box": {"type": "Polygon", "coordinates": [[[-74.285711, 40.657943], [-74.24661, 40.657943], [-74.24661, 40.6725103], [-74.285711, 40.6725103]]]}, "contained_within": [], "full_name": "Roselle Park, NJ", "attributes": {}, "id": "bcab414422facfa5", "name": "Roselle Park"}, "retweet_count": 0, "id_str": "126881658854064128"}
