{"favorited": false, "contributors": null, "truncated": false, "text": "S\u00f3 ttem eeu aqui no #TWITTER ? '--", "is_quote_status": false, "in_reply_to_status_id": null, "user": {"follow_request_sent": false, "has_extended_profile": true, "profile_use_background_image": true, "default_profile_image": false, "id": 266036874, "profile_background_image_url_https": "https://pbs.twimg.com/profile_background_images/378800000156273937/GiLLA3Bp.jpeg", "verified": false, "translator_type": "none", "profile_text_color": "3C3940", "profile_image_url_https": "https://pbs.twimg.com/profile_images/792712356019204096/BCmhizEt_normal.jpg", "profile_sidebar_fill_color": "95E8EC", "entities": {"description": {"urls": []}}, "followers_count": 1816, "profile_sidebar_border_color": "FFFFFF", "id_str": "266036874", "profile_background_color": "FAF5FA", "listed_count": 7, "is_translation_enabled": false, "utc_offset": -10800, "statuses_count": 70450, "description": "SANTOS FUTEBOL CLUBE \u26bd\u2764 \u3164", "friends_count": 193, "location": "", "profile_link_color": "1B95E0", "profile_image_url": "http://pbs.twimg.com/profile_images/792712356019204096/BCmhizEt_normal.jpg", "following": false, "geo_enabled": true, "profile_banner_url": "https://pbs.twimg.com/profile_banners/266036874/1463958088", "profile_background_image_url": "http://pbs.twimg.com/profile_background_images/378800000156273937/GiLLA3Bp.jpeg", "screen_name": "GabiDonnely", "lang": "pt", "profile_background_tile": true, "favourites_count": 8479, "name": "\u3164 DONNELY \u27b0", "notifications": false, "url": null, "created_at": "Mon Mar 14 14:54:58 +0000 2011", "contributors_enabled": false, "time_zone": "Santiago", "protected": false, "default_profile": false, "is_translator": false}, "geo": null, "id": 126867734490382336, "favorite_count": 0, "lang": "pt", "source": "<a href=\"http://twitter.com\" rel=\"nofollow\">Twitter Web Client</a>", "created_at": "Thu Oct 20 03:49:59 +0000 2011", "retweeted": false, "coordinates": null, "in_reply_to_user_id_str": null, "entities": {"symbols": [], "user_mentions": [], "hashtags": [{"indices": [20, 28], "text": "TWITTER"}], "urls": []}, "in_reply_to_status_id_str": null, "in_reply_to_screen_name": null, "in_reply_to_user_id": null, "place": null, "retweet_count": 0, "id_str": "126867734490382336"}
